{
  "formatVersion": 1,
  "database": {
    "version": 9,
    "identityHash": "16d5a21110d3a3be7e17dc72a47098ac",
    "entities": [
      {
        "tableName": "alarms",
        "createSql": "CREATE TABLE IF NOT EXISTS `${TABLE_NAME}` (`id` INTEGER PRIMARY KEY AUTOINCREMENT NOT NULL, `medicationName` TEXT NOT NULL, `hour` INTEGER NOT NULL, `minute` INTEGER NOT NULL, `repeatType` TEXT NOT NULL, `repeatInterval` INTEGER NOT NULL, `repeatDaysOfWeek` TEXT, `startDate` INTEGER NOT NULL, `endDate` INTEGER, `isActive` INTEGER NOT NULL)",
        "fields": [
          {
            "fieldPath": "id",
            "columnName": "id",
            "affinity": "INTEGER",
            "notNull": true
          },
          {
            "fieldPath": "medicationName",
            "columnName": "medicationName",
            "affinity": "TEXT",
            "notNull": true
          },
          {
            "fieldPath": "hour",
            "columnName": "hour",
            "affinity": "INTEGER",
            "notNull": true
          },
          {
            "fieldPath": "minute",
            "columnName": "minute",
            "affinity": "INTEGER",
            "notNull": true
          },
          {
            "fieldPath": "repeatType",
            "columnName": "repeatType",
            "affinity": "TEXT",
            "notNull": true
          },
          {
            "fieldPath": "repeatInterval",
            "columnName": "repeatInterval",
            "affinity": "INTEGER",
            "notNull": true
          },
          {
            "fieldPath": "repeatDaysOfWeek",
            "columnName": "repeatDaysOfWeek",
            "affinity": "TEXT",
            "notNull": false
          },
          {
            "fieldPath": "startDate",
            "columnName": "startDate",
            "affinity": "INTEGER",
            "notNull": true
          },
          {
            "fieldPath": "endDate",
            "columnName": "endDate",
            "affinity": "INTEGER",
            "notNull": false
          },
          {
            "fieldPath": "isActive",
            "columnName": "isActive",
            "affinity": "INTEGER",
            "notNull": true
          }
        ],
        "primaryKey": {
          "autoGenerate": true,
          "columnNames": [
            "id"
          ]
        },
        "indices": [],
        "foreignKeys": []
      },
      {
        "tableName": "alarm_history",
        "createSql": "CREATE TABLE IF NOT EXISTS `${TABLE_NAME}` (`id` INTEGER PRIMARY KEY AUTOINCREMENT NOT NULL, `alarmId` INTEGER NOT NULL, `logDate` TEXT NOT NULL, `status` TEXT NOT NULL, `actionTimestamp` INTEGER NOT NULL, `oneMinuteLaterTime` TEXT, `oneMinuteLaterScheduledAt` INTEGER, FOREIGN KEY(`alarmId`) REFERENCES `alarms`(`id`) ON UPDATE NO ACTION ON DELETE CASCADE )",
        "fields": [
          {
            "fieldPath": "id",
            "columnName": "id",
            "affinity": "INTEGER",
            "notNull": true
          },
          {
            "fieldPath": "alarmId",
            "columnName": "alarmId",
            "affinity": "INTEGER",
            "notNull": true
          },
          {
            "fieldPath": "logDate",
            "columnName": "logDate",
            "affinity": "TEXT",
            "notNull": true
          },
          {
            "fieldPath": "status",
            "columnName": "status",
            "affinity": "TEXT",
            "notNull": true
          },
          {
            "fieldPath": "actionTimestamp",
            "columnName": "actionTimestamp",
            "affinity": "INTEGER",
            "notNull": true
          },
          {
            "fieldPath": "oneMinuteLaterTime",
            "columnName": "oneMinuteLaterTime",
            "affinity": "TEXT",
            "notNull": false
          },
          {
            "fieldPath": "oneMinuteLaterScheduledAt",
            "columnName": "oneMinuteLaterScheduledAt",
            "affinity": "INTEGER",
            "notNull": false
          }
        ],
        "primaryKey": {
          "autoGenerate": true,
          "columnNames": [
            "id"
          ]
        },
        "indices": [],
        "foreignKeys": [
          {
            "table": "alarms",
            "onDelete": "CASCADE",
            "onUpdate": "NO ACTION",
            "columns": [
              "alarmId"
            ],
            "referencedColumns": [
              "id"
            ]
          }
        ]
      }
    ],
    "views": [],
    "setupQueries": [
      "CREATE TABLE IF NOT EXISTS room_master_table (id INTEGER PRIMARY KEY,identity_hash TEXT)",
      "INSERT OR REPLACE INTO room_master_table (id,identity_hash) VALUES(42, '16d5a21110d3a3be7e17dc72a47098ac')"
    ]
  }
}